HIIdentify/HIIdentify.py
HIIdentify/HIIdentify_plots.py
HIIdentify/__init__.py
HIIdentify-0.0.2.dist-info/LICENSE
HIIdentify-0.0.2.dist-info/METADATA
HIIdentify-0.0.2.dist-info/WHEEL
HIIdentify-0.0.2.dist-info/top_level.txt
HIIdentify-0.0.2.dist-info/RECORD
