Metadata-Version: 2.1
Name: HIIdentify
Version: 0.0.2
Summary: Identifies HII regions from H alpha emission line maps.
Home-page: https://github.com/BethanEaseman/HIIdentify
Author: Bethan Easeman
Author-email: Bethan Easeman <be329@bath.ac.uk>
License: GPLv3
Platform: UNKNOWN
Requires-Python: >=3.6
License-File: LICENSE
Requires-Dist: numpy
Requires-Dist: astropy
Requires-Dist: matplotlib
